comprehend_telemetry/__init__.py
comprehend_telemetry/span_processor.py
comprehend_telemetry/sql_analyzer.py
comprehend_telemetry/websocket_connection.py
comprehend_telemetry/wire_protocol.py
comprehend_telemetry-0.1.1.dist-info/METADATA
comprehend_telemetry-0.1.1.dist-info/WHEEL
comprehend_telemetry-0.1.1.dist-info/top_level.txt
comprehend_telemetry-0.1.1.dist-info/RECORD
