Metadata-Version: 2.4
Name: comprehend-telemetry
Version: 0.1.1
Summary: Integration of comprehend.dev with OpenTelemetry in Python
Author: comprehend.dev AB
License-Expression: LicenseRef-Proprietary-Audit
Classifier: Development Status :: 3 - Alpha
Classifier: Intended Audience :: Developers
Classifier: Programming Language :: Python :: 3
Classifier: Programming Language :: Python :: 3.8
Classifier: Programming Language :: Python :: 3.9
Classifier: Programming Language :: Python :: 3.10
Classifier: Programming Language :: Python :: 3.11
Classifier: Programming Language :: Python :: 3.12
Requires-Python: >=3.8
Requires-Dist: opentelemetry-api>=1.27.0
Requires-Dist: opentelemetry-sdk>=1.27.0
Requires-Dist: websocket-client>=1.8.0
Provides-Extra: dev
Requires-Dist: pytest>=7.4.0; extra == "dev"
Requires-Dist: pytest-cov>=4.1.0; extra == "dev"
Requires-Dist: black>=23.7.0; extra == "dev"
Requires-Dist: isort>=5.12.0; extra == "dev"
Requires-Dist: flake8>=6.0.0; extra == "dev"
Requires-Dist: mypy>=1.5.0; extra == "dev"
Requires-Dist: types-requests; extra == "dev"
